xmcp_server_weather/__init__.py
xmcp_server_weather/__main__.py
xmcp_server_weather/server.py
xmcp_server_weather-0.1.7.dist-info/METADATA
xmcp_server_weather-0.1.7.dist-info/WHEEL
xmcp_server_weather-0.1.7.dist-info/entry_points.txt
xmcp_server_weather-0.1.7.dist-info/RECORD
