Metadata-Version: 2.4
Name: xmcp-server-weather
Version: 0.1.7
Summary: 天气查询MCP服务
Requires-Python: >=3.10
Requires-Dist: beautifulsoup4>=4.13.4
Requires-Dist: httpx>=0.28.1
Requires-Dist: mcp[cli]>=1.9.4
